AddTwoNum/Adder.py
AddTwoNum/__init__.py
AddTwoNumSeventhSon-0.0.1.dist-info/METADATA
AddTwoNumSeventhSon-0.0.1.dist-info/WHEEL
AddTwoNumSeventhSon-0.0.1.dist-info/top_level.txt
AddTwoNumSeventhSon-0.0.1.dist-info/RECORD
