Metadata-Version: 2.1
Name: AddTwoNumSeventhSon
Version: 0.0.1
Summary: Add two numbers
Author: 
Author-email: 
Keywords: python,add two num
Classifier: Development Status :: 1 - Planning
Classifier: Intended Audience :: Developers
Classifier: Programming Language :: Python :: 3
Classifier: Operating System :: Unix
Classifier: Operating System :: MacOS :: MacOS X
Classifier: Operating System :: Microsoft :: Windows
